{
  "$schema": "../.hmiframework/Schema/ControlDescription.Schema.json",
  "apiVersion": 1,
  "name": "Philips_Hue_ColorControl",
  "namespace": "TcHmi.Controls.Philips_Hue_Color",
  "displayName": "Philips_Hue_ColorControl",
  "version": {
    "full": "1.0.0.0",
    "major": 1,
    "minor": 0,
    "revision": 0,
    "build": 0
  },
  "visible": true,
  "themeable": "Standard",
  "base": "TcHmi.Controls.System.TcHmiControl",
  "description": "This description text will be used as a Tooltip in Visual Studio.",
  "properties": {
    "containerControl": false,
    "geometry": {
      "width": 150,
      "height": 150
    }
  },
  "template": "Template.html",
  "icons": [
    {
      "name": "Icons/16x16.png",
      "width": 16,
      "height": 16
    },
    {
      "name": "Icons/24x24.png",
      "width": 24,
      "height": 24
    },
    {
      "name": "Icons/32x32.png",
      "width": 32,
      "height": 32
    },
    {
      "name": "Icons/64x64.png",
      "width": 64,
      "height": 64
    }
  ],
  "dependencyFiles": [
    {
      "name": "Philips_Hue_ColorControl.js",
      "type": "JavaScript",
      "description": "Contains all the main logic."
    },
    {
      "name": "Style.css",
      "type": "Stylesheet",
      "description": "Theme independent style"
    },
    {
      "name": "jslibs/color-disc.min.js",
      "type": "JavaScript",
      "description": "Color disc"
    }

  ],
  "themes": {
    "Base": {
      "resources": [
        {
          "name": "Themes/Base/Style.css",
          "type": "Stylesheet",
          "description": "Theme dependent style"
        }
      ]
    }
  },
  "attributes": [
    {
      "name": "data-tchmi-philips-hue-showAdvanced",
      "displayName": "ShowAdvanced",
      "propertyName": "ShowAdvanced",
      "propertySetterName": "setShowAdvanced",
      "propertyGetterName": "getShowAdvanced",
      "visible": true,
      "type": "tchmi:general#/definitions/Boolean",
      "category": "Common",
      "description": "Show or hide advanced functions",
      "requiredOnCompile": false,
      "readOnly": false,
      "bindable": false,
      "heritable": true,
      "defaultValue": false,
      "defaultValueInternal": false
    }

  ],
  "attributeCategories": [],
  "functions": [],
  "events": [],
  "dataTypes": [
    {
      "schema": "Schema/Types.Schema.json"
    }
  ]
}